langcode/__init__.py
langcode/jupyter/__init__.py
langcode/jupyter/_from_remote.py
langcode/jupyter/_local.py
langcode/jupyter/_main.py
langcode/jupyter/_protocol.py
langcode-0.1.6.dist-info/LICENSE
langcode-0.1.6.dist-info/METADATA
langcode-0.1.6.dist-info/WHEEL
langcode-0.1.6.dist-info/RECORD
