Metadata-Version: 2.1
Name: langcode
Version: 0.1.6
Summary: 
Home-page: https://github.com/keell0renz/langcode
License: MIT
Author: Your Name
Author-email: you@example.com
Requires-Python: >=3.7,<4.0
Classifier: License :: OSI Approved :: MIT License
Classifier: Programming Language :: Python :: 3
Classifier: Programming Language :: Python :: 3.7
Classifier: Programming Language :: Python :: 3.8
Classifier: Programming Language :: Python :: 3.9
Classifier: Programming Language :: Python :: 3.10
Classifier: Programming Language :: Python :: 3.11
Classifier: Programming Language :: Python :: 3.12
Requires-Dist: ipykernel (>=6.29.4,<7.0.0)
Requires-Dist: jupyter (>=1.0.0,<2.0.0)
Requires-Dist: jupyter-client (>=8.6.2,<9.0.0)
Project-URL: Documentation, https://github.com/keell0renz/langcode
Project-URL: Repository, https://github.com/keell0renz/langcode
